{
    "attributes": {
        "_description": {
            "key": "_description",
            "type": "STRING",
            "value": "Check that ITS-S discards data with a cryptographically invalid signature."
        },
        "_locations": {
            "key": "_locations",
            "type": "LIST",
            "value": ["/Documents/TS103096-02.xhtml/27a9f4ee-c84e-4ebf-9512-492f819f7c33"]
        },
        "_type": {
            "key": "_type",
            "type": "STRING",
            "value": "Requirement"
        }
    },
    "uuid": "96b72d90-5414-4bd5-994d-f06455b5589c"
}