{
    "attributes": {
        "_description": {
            "isGenerated": false,
            "key": "_description",
            "origin": "5415f6e1-2985-4815-aeb4-d68f2376eb87",
            "type": "STRING",
            "value": "If ITS-S sends a secured DENM check that the sent SecuredMessage contains exactly one HeaderField generation_time which is inside the validity time of the certificate referenced by the signer_info."
        },
        "_locations": {
            "isGenerated": false,
            "key": "_locations",
            "origin": "5415f6e1-2985-4815-aeb4-d68f2376eb87",
            "type": "LIST",
            "value": [
                "/Documents/Draft_ETSI_TS_103 097 v1.1.14.xhtml/e1c8b3e0-5da0-4e8d-8355-563039c7cdc7",
                "/Documents/Draft_ETSI_TS_103 097 v1.1.14.xhtml/9d288386-4b6a-46cc-9bd4-5be9d85696d0",
                "/Documents/Draft_ETSI_TS_103 097 v1.1.14.xhtml/d8ce00e7-f3e1-479b-8ce8-73861f492c7b"
            ]
        },
        "_name": {
            "isGenerated": false,
            "key": "_name",
            "origin": "5415f6e1-2985-4815-aeb4-d68f2376eb87",
            "type": "STRING",
            "value": "04. Check generation time"
        },
        "_type": {
            "isGenerated": false,
            "key": "_type",
            "origin": "5415f6e1-2985-4815-aeb4-d68f2376eb87",
            "type": "STRING",
            "value": "Requirement"
        }
    },
    "uuid": "5415f6e1-2985-4815-aeb4-d68f2376eb87"
}