{
    "attributes": {
        "_description": {
            "key": "_description",
            "type": "STRING",
            "value": "Check that ITS-S generates valid authorization request with a CSR certificate with name of length > 0 and <= 32."
        },
        "_locations": {
            "key": "_locations",
            "type": "LIST",
            "value": ["/Documents/TS103096-02.xhtml/9901aa36-802c-4c97-a313-a7e1f727d935"]
        },
        "_type": {
            "key": "_type",
            "type": "STRING",
            "value": "Requirement"
        }
    },
    "uuid": "5e27b654-cc40-49c9-b79d-9dfa436e53bb"
}